flagify/__init__.py
flagify/src/flag.py
flagify/src/util.py
flagify-1.5.0.dist-info/LICENSE
flagify-1.5.0.dist-info/METADATA
flagify-1.5.0.dist-info/WHEEL
flagify-1.5.0.dist-info/top_level.txt
flagify-1.5.0.dist-info/RECORD
