Metadata-Version: 2.1
Name: flagify
Version: 1.5.0
Summary: put/remove flags for files and folders
Author: Moses Dastmard
License: UNKNOWN
Platform: UNKNOWN
License-File: LICENSE
Requires-Dist: mpath
